PACMANCharge/PACMaN.py
PACMANCharge/__init__.py
PACMANCharge/atom_init.json
test/Cu-BTC.cif
test/__init__.py
test/test.py
PACMANCharge-0.0.8.dist-info/LICENSE
PACMANCharge-0.0.8.dist-info/METADATA
PACMANCharge-0.0.8.dist-info/WHEEL
PACMANCharge-0.0.8.dist-info/top_level.txt
PACMANCharge-0.0.8.dist-info/RECORD
