Metadata-Version: 2.1
Name: PACMANCharge
Version: 0.0.8
Summary: Partial Atomic Charges for Porous Materials based on Graph Convolutional Neural Network (PACMAN)
Home-page: https://github.com/sxm13/PACMAN
Author: Guobin Zhao
Author-email: sxmzhaogb@gmai.com
License: MIT
Classifier: Programming Language :: Python :: 3
Classifier: License :: OSI Approved :: MIT License
License-File: LICENSE
Requires-Dist: requests
Requires-Dist: numpy (>=1.13.3)
Requires-Dist: pymatgen (>=2018.6.11)
Requires-Dist: ase (>=3.19)
Requires-Dist: tqdm (>=4.15)
Requires-Dist: pandas (>=0.20.3)
Requires-Dist: scikit-learn (>=0.19.1)
Requires-Dist: joblib (>=0.13.2)
Requires-Dist: torch
